[{"text": "قَالَ هَلْ أَنتُم مُّطَّلِعُونَ", "sura_id": 37, "type": 0, "id": 3842, "aya_id": 54}, {"text": "قال هل أنتم مطلعون", "sura_id": 37, "type": 1, "id": 10078, "aya_id": 54}, {"text": "54 - (قال) ذلك القائل لإخوانه (هل أنتم مطلعون) معب إلى النار لننظر حاله فيقولون لا \r\n", "sura_id": 37, "type": 2, "id": 28786, "aya_id": 54}, {"text": "قال هذا المؤمن الذي أُدخل الجنة لأصحابه: هل أنتم مُطَّلعون لنرى مصير ذلك القرين؟\r\n", "sura_id": 37, "type": 3, "id": 35022, "aya_id": 54}, {"text": " <font color=red>قَالَ هَلْ أَنْتُمْ مُطَّلِعُونَ</font><BR><p>أَيْ مُشْرِفُونَ يَقُول الْمُؤْمِن لِأَصْحَابِهِ وَجُلَسَائِهِ مِنْ أَهْل الْجَنَّة .</p><BR> <br> ", "sura_id": 37, "type": 4, "id": 40554, "aya_id": 54}]