[{"text": "وَلَقَدْ كَذَّبَ الَّذِينَ مِن قَبْلِهِمْ فَكَيْفَ كَانَ نَكِيرِ", "sura_id": 67, "type": 0, "id": 5259, "aya_id": 18}, {"text": "ولقد كذب الذين من قبلهم فكيف كان نكير", "sura_id": 67, "type": 1, "id": 11495, "aya_id": 18}, {"text": "18 - (ولقد كذب الذين من قبلهم) من الأمم (فكيف كان نكير) إنكاري عليهم بالتكذيب عند إهلاكهم أي أنه حق \r\n", "sura_id": 67, "type": 2, "id": 30203, "aya_id": 18}, {"text": "ولقد كذَّب الذين كانوا قبل كفار \"مكة\" كقوم نوح وعاد وثمود رسلهم, فكيف كان إنكاري عليهم, وتغييري ما بهم من نعمة بإنزال العذاب بهم وإهلاكهم؟\r\n", "sura_id": 67, "type": 3, "id": 36439, "aya_id": 18}, {"text": " <font color=red>وَلَقَدْ كَذَّبَ الَّذِينَ مِنْ قَبْلِهِمْ فَكَيْفَ كَانَ نَكِيرِ</font><BR><p>ثُمَّ قَالَ تَعَالَى \" وَلَقَدْ كَذَّبَ الَّذِينَ مِنْ قَبْلهمْ \" أَيْ مِنْ الْأُمَم السَّالِفَة وَالْقُرُون الْخَالِيَة \" فَكَيْف كَانَ نَكِير \" أَيْ فَكَيْف كَانَ إِنْكَارِي عَلَيْهِمْ وَمُعَاقَبَتِي لَهُمْ ؟ أَيْ عَظِيمًا شَدِيدًا أَلِيمًا .</p><BR> <br> ", "sura_id": 67, "type": 4, "id": 42341, "aya_id": 18}]