[{"text": "لُعِنَ الَّذِينَ كَفَرُواْ مِن بَنِي إِسْرَائِيلَ عَلَى لِسَانِ دَاوُودَ وَعِيسَى ابْنِ مَرْيَمَ ذَلِكَ بِمَا عَصَوا وَّكَانُواْ يَعْتَدُونَ", "sura_id": 5, "type": 0, "id": 747, "aya_id": 78}, {"text": "لعن الذين كفروا من بني إسرائيل على لسان داود وعيسى ابن مريم ذلك بما عصوا وكانوا يعتدون", "sura_id": 5, "type": 1, "id": 6983, "aya_id": 78}, {"text": "78 - (لعن الذين كفروا من بني إسرائيل على لسان داود) بأن دعا عليهم فمسخوا قردة وهم أصحاب أيلة (وعيسى ابن مريم) بأن دعا عليهم فمسخوا خنازير وهم أصحاب المائدة (ذلك) اللعن (بما عصوا وكانوا يعتدون) \r\n", "sura_id": 5, "type": 2, "id": 25691, "aya_id": 78}, {"text": "يخبر تعالى أنه طرد من رحمته الكافرين من بني إسرائيل في الكتاب الذي أنزله على داود -عليه السلام- وهو الزَّبور, وفي الكتاب الذي أنزله على عيسى - عليه السلام - وهو الإنجيل; بسبب عصيانهم واعتدائهم على حرمات الله.\r\n", "sura_id": 5, "type": 3, "id": 31927, "aya_id": 78}, {"text": " <font color=red>لُعِنَ الَّذِينَ كَفَرُوا مِنْ بَنِي إِسْرَائِيلَ عَلَى لِسَانِ دَاوُدَ وَعِيسَى ابْنِ مَرْيَمَ ذَلِكَ بِمَا عَصَوْا وَكَانُوا يَعْتَدُونَ</font><BR><p>يُخْبِر تَعَالَى أَنَّهُ لَعَنَ الْكَافِرِينَ مِنْ بَنِي إِسْرَائِيل مِنْ دَهْر طَوِيل فِيمَا أَنْزَلَهُ عَلَى دَاوُدَ نَبِيّه - عَلَيْهِ السَّلَام - وَعَلَى لِسَان عِيسَى اِبْن مَرْيَم بِسَبَبِ عِصْيَانهمْ لِلَّهِ وَاعْتِدَائِهِمْ عَلَى خَلْقه قَالَ الْعَوْفِيّ : عَنْ اِبْن عَبَّاس لُعِنُوا فِي التَّوْرَاة وَالْإِنْجِيل وَفِي الزَّبُور وَفِي الْفُرْقَان ثُمَّ بَيَّنَ حَالهمْ فِيمَا كَانُوا يَعْتَمِدُونَهُ فِي زَمَانهمْ .</p><BR> <br> ", "sura_id": 5, "type": 4, "id": 41533, "aya_id": 78}]