[{"text": "وَجَنَّاتٍ وَعُيُونٍ", "sura_id": 26, "type": 0, "id": 3066, "aya_id": 134}, {"text": "وجنات وعيون", "sura_id": 26, "type": 1, "id": 9302, "aya_id": 134}, {"text": "134 - (وجنات) بساتين (وعيون) أنهار \r\n", "sura_id": 26, "type": 2, "id": 28010, "aya_id": 134}, {"text": "وأعطاكم البساتين المثمرة, وفجَّر لكم الماء من العيون الجارية.\r\n", "sura_id": 26, "type": 3, "id": 34246, "aya_id": 134}, {"text": " <font color=red>وَجَنَّاتٍ وَعُيُونٍ</font><BR><p>فَقَالَ : \" وَاتَّقُوا الَّذِي أَمَدَّكُمْ بِمَا تَعْلَمُونَ أَمَدَّكُمْ بِأَنْعَامٍ وَبَنِينَ وَجَنَّات وَعُيُون إِنِّي أَخَاف عَلَيْكُمْ عَذَاب يَوْم عَظِيم \" أَيْ إِنْ كَذَّبْتُمْ وَخَالَفْتُمْ فَدَعَاهُمْ إِلَى اللَّه بِالتَّرْغِيبِ وَالتَّرْهِيب فَمَا نَفَعَ فِيهِمْ .</p><BR> <br> ", "sura_id": 26, "type": 4, "id": 39405, "aya_id": 134}]