[{"text": "يَا أَيُّهَا النَّاسُ قَدْ جَاءتْكُم مَّوْعِظَةٌ مِّن رَّبِّكُمْ وَشِفَاء لِّمَا فِي الصُّدُورِ وَهُدًى وَرَحْمَةٌ لِّلْمُؤْمِنِينَ", "sura_id": 10, "type": 0, "id": 1421, "aya_id": 57}, {"text": "يا أيها الناس قد جاءتكم موعظة من ربكم وشفاء لما في الصدور وهدى ورحمة للمؤمنين", "sura_id": 10, "type": 1, "id": 7657, "aya_id": 57}, {"text": "57 - (يا أيها الناس) أي أهل مكة (قد جاءتكم موعظة من ربكم) كتاب فيه ما لكم وما عليكم وهو القرآن (وشفاء) دواء (لما في الصدور) من العقائد الفاسدة والشكوك (وهدى) من الضلال (ورحمة للمؤمنين) به \r\n", "sura_id": 10, "type": 2, "id": 26365, "aya_id": 57}, {"text": "يا أيها الناس قد جاءتكم موعظة من ربكم تذكِّركم عقاب الله وتخوفكم وعيده, وهي القرآن وما اشتمل عليه من الآيات والعظات لإصلاح أخلاقكم وأعمالكم, وفيه دواء لما في القلوب من الجهل والشرك وسائر الأمراض, ورشد لمن اتبعه من الخلق فينجيه من الهلاك, جعله سبحانه وتعالى نعمة ورحمة للمؤمنين, وخصَّهم بذلك; لأنهم المنتفعون بالإيمان, وأما الكافرون فهو عليهم عَمَى.\r\n", "sura_id": 10, "type": 3, "id": 32601, "aya_id": 57}, {"text": " <font color=red>يَا أَيُّهَا النَّاسُ قَدْ جَاءَتْكُمْ مَوْعِظَةٌ مِنْ رَبِّكُمْ وَشِفَاءٌ لِمَا فِي الصُّدُورِ وَهُدًى وَرَحْمَةٌ</font><BR><p>يَقُول تَعَالَى مُمْتَنًّا عَلَى خَلْقه بِمَا أَنْزَلَهُ مِنْ الْقُرْآن الْعَظِيم عَلَى رَسُوله الْكَرِيم \" يَا أَيّهَا النَّاس قَدْ جَاءَتْكُمْ مَوْعِظَة مِنْ رَبّكُمْ \" أَيْ زَاجِر عَنْ الْفَوَاحِش \" وَشِفَاء لِمَا فِي الصُّدُور \" أَيْ مِنْ الشُّبَه وَالشُّكُوك وَهُوَ إِزَالَة مَا فِيهَا مِنْ رِجْس وَدَنَس وَهُدًى وَرَحْمَة أَيْ يَحْصُل بِهِ الْهِدَايَة وَالرَّحْمَة مِنْ اللَّه تَعَالَى ; وَإِنَّمَا ذَلِكَ لِلْمُؤْمِنِينَ بِهِ وَالْمُصَدِّقِينَ الْمُوقِنِينَ بِمَا فِيهِ كَقَوْلِهِ تَعَالَى \" وَنُنَزِّل مِنْ الْقُرْآن مَا هُوَ شِفَاء وَرَحْمَة لِلْمُؤْمِنِينَ وَلَا يَزِيد الظَّالِمِينَ إِلَّا خَسَارًا \" وَقَوْله \" قُلْ هُوَ لِلَّذِينَ آمَنُوا هُدًى وَشِفَاء \" الْآيَة .</p><BR> <br> ", "sura_id": 10, "type": 4, "id": 37486, "aya_id": 57}]