[{"text": "ثُمَّ نُنَجِّي رُسُلَنَا وَالَّذِينَ آمَنُواْ كَذَلِكَ حَقًّا عَلَيْنَا نُنجِ الْمُؤْمِنِينَ", "sura_id": 10, "type": 0, "id": 1467, "aya_id": 103}, {"text": "ثم ننجي رسلنا والذين آمنوا كذلك حقا علينا ننج المؤمنين", "sura_id": 10, "type": 1, "id": 7703, "aya_id": 103}, {"text": "103 - (ثم ننجّي) المضارع لحكاية الحال الماضي (رسلنا والذين آمنوا) من العذاب (كذلك) الإنجاء (حقاً علينا ننج المؤمنين) النبي صلى الله عليه وسلم وأصحابه حين تعذيب المشركين \r\n", "sura_id": 10, "type": 2, "id": 26411, "aya_id": 103}, {"text": "ثم ننجِّي رسلنا والذين آمنوا معهم, وكما نجينا أولئك ننجِّيك -أيها الرسول- ومن آمن بك تفضلا منَّا ورحمة.\r\n", "sura_id": 10, "type": 3, "id": 32647, "aya_id": 103}, {"text": " <font color=red>ثُمَّ نُنَجِّي رُسُلَنَا وَالَّذِينَ آمَنُوا كَذَلِكَ حَقًّا عَلَيْنَا نُنْجِ الْمُؤْمِنِينَ</font><BR><p>\" كَذَلِكَ حَقًّا عَلَيْنَا نُنْجِي الْمُؤْمِنِينَ \" أَيْ حَقًّا أَوْجَبَهُ اللَّه عَلَى نَفْسه الْكَرِيمَة كَقَوْلِهِ \" كَتَبَ رَبّكُمْ عَلَى نَفْسه الرَّحْمَة \" وَكَمَا جَاءَ فِي الصَّحِيحَيْنِ عَنْ رَسُول اللَّه صَلَّى اللَّه عَلَيْهِ وَسَلَّمَ أَنَّهُ قَالَ \" إِنَّ اللَّه كَتَبَ كِتَابًا فَهُوَ عِنْده فَوْق الْعَرْش : إِنَّ رَحْمَتِي سَبَقَتْ غَضَبِي \" .</p><BR> <br> ", "sura_id": 10, "type": 4, "id": 37429, "aya_id": 103}]