[{"text": "إِذْ قَالَتِ امْرَأَةُ عِمْرَانَ رَبِّ إِنِّي نَذَرْتُ لَكَ مَا فِي بَطْنِي مُحَرَّرًا فَتَقَبَّلْ مِنِّي إِنَّكَ أَنتَ السَّمِيعُ الْعَلِيمُ", "sura_id": 3, "type": 0, "id": 328, "aya_id": 35}, {"text": "إذ قالت امرأة عمران رب إني نذرت لك ما في بطني محررا فتقبل مني إنك أنت السميع العليم", "sura_id": 3, "type": 1, "id": 6564, "aya_id": 35}, {"text": "35 - اذكر (إذ قالت امرأة عمران) حنة لما أسنت واشتاقت للولد فدعت الله وأحست بالحمل يا (رب إني نذرت) أن أجعل (لك ما في بطني محرراً) عتيقاً خالصاً من شواغل الدنيا لخدمة بيتك المقدس (فتقبل مني إنك أنت السميع) للدعاء (العليم) بالنيات ، وهلك عمران وهي حامل \r\n", "sura_id": 3, "type": 2, "id": 25272, "aya_id": 35}, {"text": "اذكر -أيها الرسول- ما كان من أمر مريم وأمها وابنها عيسى عليه السلام; لتردَّ بذلك على من ادعوا أُلوهية عيسى أو بنوَّته لله سبحانه, إذ قالت امرأة عمران حين حملت: يا ربِّ إني جعلت لك ما في بطني خالصا لك, لخدمة \"بيت المقدس\", فتقبَّل مني; إنك أنت وحدك السميع لدعائي, العليم بنيتي.\r\n", "sura_id": 3, "type": 3, "id": 31508, "aya_id": 35}, {"text": " <font color=red>إِذْ قَالَتِ امْرَأَةُ عِمْرَانَ رَبِّ إِنِّي نَذَرْتُ لَكَ مَا فِي بَطْنِي مُحَرَّرًا فَتَقَبَّلْ مِنِّي إِنَّكَ أَنْتَ السَّمِيعُ الْعَلِيمُ</font><BR><p>اِمْرَأَة عِمْرَان هَذِهِ هِيَ أُمّ مَرْيَم عَلَيْهَا السَّلَام وَهِيَ حنة بِنْت فاقوذ . قَالَ مُحَمَّد بْن إِسْحَق : وَكَانَتْ اِمْرَأَة لَا تَحْمِل فَرَأَتْ يَوْمًا طَائِرًا يَزُقّ فَرْخه فَاشْتَهَتْ الْوَلَد فَدَعَتْ اللَّه تَعَالَى أَنْ يَهَبهَا وَلَدًا فَاسْتَجَابَ اللَّه دُعَاءَهَا فَوَاقَعَهَا زَوْجهَا فَحَمَلَتْ مِنْهُ فَلَمَّا تَحَقَّقَتْ الْحَمْل نَذَرَتْ أَنْ يَكُون مُحَرَّرًا أَيْ خَالِصًا مُفَرَّغًا لِلْعِبَادَةِ لِخِدْمَةِ بَيْت الْمَقْدِس فَقَالَتْ : يَا رَبّ \" إِنِّي نَذَرْت لَك مَا فِي بَطْنِي مُحَرَّرًا فَتَقَبَّلْ مِنِّي إِنَّك أَنْتَ السَّمِيع الْعَلِيم \" أَيْ السَّمِيع لِدُعَائِي الْعَلِيم بِنِيَّتِي وَلَمْ تَكُنْ تَعْلَم مَا فِي بَطْنهَا أَذَكَرًا أَمْ أُنْثَى .</p><BR> <br> ", "sura_id": 3, "type": 4, "id": 39972, "aya_id": 35}]