[{"text": "وَآيَةٌ لَّهُمُ الْأَرْضُ الْمَيْتَةُ أَحْيَيْنَاهَا وَأَخْرَجْنَا مِنْهَا حَبًّا فَمِنْهُ يَأْكُلُونَ", "sura_id": 36, "type": 0, "id": 3738, "aya_id": 33}, {"text": "وآية لهم الأرض الميتة أحييناها وأخرجنا منها حبا فمنه يأكلون", "sura_id": 36, "type": 1, "id": 9974, "aya_id": 33}, {"text": "33 - (وآية لهم) على البعث خبر مقدم (الأرض الميتة) بالتخفيف والتشديد (أحييناها) بالماء مبتدأ (وأخرجنا منها حبا) كالحنطة (فمنه يأكلون) \r\n", "sura_id": 36, "type": 2, "id": 28682, "aya_id": 33}, {"text": "ودلالة لهؤلاء المشركين على قدرة الله على البعث والنشور: هذه الأرض الميتة التي لا نبات فيها, أحييناها بإنزال الماء, وأخرجنا منها أنواع النبات مما يأكل الناس والأنعام, ومن أحيا الأرض بالنبات أحيا الخلق بعد الممات.\r\n", "sura_id": 36, "type": 3, "id": 34918, "aya_id": 33}, {"text": " <font color=red>وَآيَةٌ لَهُمُ الْأَرْضُ الْمَيْتَةُ أَحْيَيْنَاهَا وَأَخْرَجْنَا مِنْهَا حَبًّا فَمِنْهُ يَأْكُلُونَ</font><BR><p>يَقُول تَبَارَكَ وَتَعَالَى \" وَآيَة لَهُمْ \" أَيْ دَلَالَة لَهُمْ عَلَى وُجُود الصَّانِع وَقُدْرَته التَّامَّة وَإِحْيَائِهِ الْمَوْتَى \" الْأَرْض الْمَيْتَة \" أَيْ إِذَا كَانَتْ مَيْتَة هَامِدَة لَا شَيْء فِيهَا مِنْ النَّبَات فَإِذَا أَنْزَلَ اللَّه تَعَالَى عَلَيْهَا الْمَاء اِهْتَزَّتْ وَرَبَتْ وَأَنْبَتَتْ مِنْ كُلّ زَوْج بَهِيج وَلِهَذَا قَالَ تَعَالَى : \" أَحْيَيْنَاهَا وَأَخْرَجْنَا مِنْهَا حَبًّا فَمِنْهُ يَأْكُلُونَ \" أَيْ جَعَلْنَا رِزْقًا لَهُمْ وَلِأَنْعَامِهِمْ .</p><BR> <br> ", "sura_id": 36, "type": 4, "id": 40365, "aya_id": 33}]