[{"text": "كَلَّا بَلْ تُحِبُّونَ الْعَاجِلَةَ", "sura_id": 75, "type": 0, "id": 5571, "aya_id": 20}, {"text": "كلا بل تحبون العاجلة", "sura_id": 75, "type": 1, "id": 11807, "aya_id": 20}, {"text": "20 - (كلا) استفتاح بمعنى ألا (بل تحبون العاجلة) الدنيا بالتاء والياء في الفعلين \r\n", "sura_id": 75, "type": 2, "id": 30515, "aya_id": 20}, {"text": "ليس الأمر كما زعمتم- يا معشر المشركين- أن لا بعث ولا جزاء، بل أنتم قوم تحبون الدنيا وزينتها،\r\n", "sura_id": 75, "type": 3, "id": 36751, "aya_id": 20}, {"text": " <font color=red>كَلَّا بَلْ تُحِبُّونَ الْعَاجِلَةَ</font><BR><p>أَيْ إِنَّمَا يَحْمِلهُمْ عَلَى التَّكْذِيب بِيَوْمِ الْقِيَامَة وَمُخَالَفَة مَا أَنْزَلَهُ اللَّه عَزَّ وَجَلَّ عَلَى رَسُوله صَلَّى اللَّه عَلَيْهِ وَسَلَّمَ مِنْ الْوَحْي الْحَقّ وَالْقُرْآن الْعَظِيم .</p><BR> <br> ", "sura_id": 75, "type": 4, "id": 42860, "aya_id": 20}]