[{"text": "إِنَّهُ كَانَ فَرِيقٌ مِّنْ عِبَادِي يَقُولُونَ رَبَّنَا آمَنَّا فَاغْفِرْ لَنَا وَارْحَمْنَا وَأَنتَ خَيْرُ الرَّاحِمِينَ", "sura_id": 23, "type": 0, "id": 2782, "aya_id": 109}, {"text": "إنه كان فريق من عبادي يقولون ربنا آمنا فاغفر لنا وارحمنا وأنت خير الراحمين", "sura_id": 23, "type": 1, "id": 9018, "aya_id": 109}, {"text": "109 - (إنه كان فريق من عبادي) هم المهاجرون (يقولون ربنا آمنا فاغفر لنا وارحمنا وأنت خير الراحمين) \r\n", "sura_id": 23, "type": 2, "id": 27726, "aya_id": 109}, {"text": "إنه كان فريق من عبادي- وهم المؤمنون- يَدْعون: ربنا آمنا فاستر ذنوبنا، وارحمنا، وأنت خير الراحمين.\r\n", "sura_id": 23, "type": 3, "id": 33962, "aya_id": 109}, {"text": " <font color=red>إِنَّهُ كَانَ فَرِيقٌ مِنْ عِبَادِي يَقُولُونَ رَبَّنَا آمَنَّا فَاغْفِرْ لَنَا وَارْحَمْنَا وَأَنْتَ خَيْرُ الرَّاحِمِينَ</font><BR><p>فَقَالَ تَعَالَى\" إِنَّهُ كَانَ فَرِيق مِنْ عِبَادِي يَقُولُونَ رَبّنَا آمَنَّا فَاغْفِرْ لَنَا وَارْحَمْنَا وَأَنْتَ خَيْر الرَّاحِمِينَ فَاتَّخَذْتُمُوهُمْ سِخْرِيًّا \" أَيْ فَسَخِرْتُمْ مِنْهُمْ فِي دُعَائِهِمْ إِيَّايَ وَتَضَرُّعهمْ إِلَيَّ \" حَتَّى أَنْسَوْكُمْ ذِكْرِي \" أَيْ حَمَلَكُمْ بُغْضهمْ عَلَيَّ أَنْ نَسِيتُمْ مُعَامَلَتِي \" وَكُنْتُمْ مِنْهُمْ تَضْحَكُونَ \" أَيْ مِنْ صَنِيعهمْ وَعِبَادَتهمْ كَمَا قَالَ تَعَالَى \" إِنَّ الَّذِينَ أَجْرَمُوا كَانُوا مِنْ الَّذِينَ آمَنُوا يَضْحَكُونَ وَإِذَا مَرُّوا بِهِمْ يَتَغَامَزُونَ \" أَيْ يَلْمِزُونَهُمْ اِسْتِهْزَاء ثُمَّ أَخْبَرَ تَعَالَى عَمَّا جَازَى بِهِ أَوْلِيَاءَهُ وَعِبَاده الصَّالِحِينَ .</p><BR> <br> ", "sura_id": 23, "type": 4, "id": 39118, "aya_id": 109}]