[{"sura_id": 27, "segs": [{"y": 0, "x": 0, "w": 290, "h": 28}, {"y": 28, "x": 194, "w": 96, "h": 28}], "aya_id": 23}, {"sura_id": 27, "segs": [{"y": 28, "x": 0, "w": 194, "h": 28}, {"y": 57, "x": 0, "w": 290, "h": 28}, {"y": 85, "x": 181, "w": 109, "h": 28}], "aya_id": 24}, {"sura_id": 27, "segs": [{"y": 85, "x": 0, "w": 181, "h": 28}, {"y": 114, "x": 33, "w": 257, "h": 28}], "aya_id": 25}, {"sura_id": 27, "segs": [{"y": 114, "x": 0, "w": 33, "h": 28}, {"y": 143, "x": 78, "w": 212, "h": 28}], "aya_id": 26}, {"sura_id": 27, "segs": [{"y": 143, "x": 0, "w": 78, "h": 28}, {"y": 171, "x": 112, "w": 178, "h": 28}], "aya_id": 27}, {"sura_id": 27, "segs": [{"y": 171, "x": 0, "w": 112, "h": 28}, {"y": 200, "x": 63, "w": 227, "h": 28}], "aya_id": 28}, {"sura_id": 27, "segs": [{"y": 200, "x": 0, "w": 63, "h": 28}, {"y": 228, "x": 142, "w": 148, "h": 28}], "aya_id": 29}, {"sura_id": 27, "segs": [{"y": 228, "x": 0, "w": 142, "h": 28}, {"y": 257, "x": 165, "w": 125, "h": 28}], "aya_id": 30}, {"sura_id": 27, "segs": [{"y": 257, "x": 19, "w": 146, "h": 28}], "aya_id": 31}, {"sura_id": 27, "segs": [{"y": 257, "x": 0, "w": 19, "h": 28}, {"y": 286, "x": 0, "w": 290, "h": 28}, {"y": 314, "x": 222, "w": 68, "h": 28}], "aya_id": 32}, {"sura_id": 27, "segs": [{"y": 314, "x": 0, "w": 222, "h": 28}, {"y": 343, "x": 179, "w": 111, "h": 28}], "aya_id": 33}, {"sura_id": 27, "segs": [{"y": 343, "x": 0, "w": 179, "h": 28}, {"y": 371, "x": 16, "w": 274, "h": 28}], "aya_id": 34}, {"sura_id": 27, "segs": [{"y": 371, "x": 0, "w": 16, "h": 28}, {"y": 400, "x": 16, "w": 274, "h": 28}], "aya_id": 35}]